papermerge_restapi_client/__init__.py
papermerge_restapi_client/api_client.py
papermerge_restapi_client/configuration.py
papermerge_restapi_client/exceptions.py
papermerge_restapi_client/rest.py
papermerge_restapi_client/schemas.py
papermerge_restapi_client/apis/__init__.py
papermerge_restapi_client/apis/path_to_api.py
papermerge_restapi_client/apis/tag_to_api.py
papermerge_restapi_client/apis/paths/__init__.py
papermerge_restapi_client/apis/paths/api_auth_login_.py
papermerge_restapi_client/apis/paths/api_auth_logout_.py
papermerge_restapi_client/apis/paths/api_auth_logoutall_.py
papermerge_restapi_client/apis/paths/api_document_versions_id_.py
papermerge_restapi_client/apis/paths/api_document_versions_id_download_.py
papermerge_restapi_client/apis/paths/api_documents_.py
papermerge_restapi_client/apis/paths/api_documents_document_id_upload_file_name.py
papermerge_restapi_client/apis/paths/api_documents_id_.py
papermerge_restapi_client/apis/paths/api_documents_id_ocr_text.py
papermerge_restapi_client/apis/paths/api_documents_merge_.py
papermerge_restapi_client/apis/paths/api_folders_.py
papermerge_restapi_client/apis/paths/api_folders_id_.py
papermerge_restapi_client/apis/paths/api_groups_.py
papermerge_restapi_client/apis/paths/api_groups_id_.py
papermerge_restapi_client/apis/paths/api_nodes_.py
papermerge_restapi_client/apis/paths/api_nodes_download_.py
papermerge_restapi_client/apis/paths/api_nodes_id_.py
papermerge_restapi_client/apis/paths/api_nodes_id_tags_.py
papermerge_restapi_client/apis/paths/api_nodes_inboxcount_.py
papermerge_restapi_client/apis/paths/api_nodes_move_.py
papermerge_restapi_client/apis/paths/api_ocr_.py
papermerge_restapi_client/apis/paths/api_pages_.py
papermerge_restapi_client/apis/paths/api_pages_id_.py
papermerge_restapi_client/apis/paths/api_pages_move_to_document_.py
papermerge_restapi_client/apis/paths/api_pages_move_to_folder_.py
papermerge_restapi_client/apis/paths/api_pages_reorder_.py
papermerge_restapi_client-1.0.0.dist-info/METADATA
papermerge_restapi_client-1.0.0.dist-info/WHEEL
papermerge_restapi_client-1.0.0.dist-info/top_level.txt
papermerge_restapi_client-1.0.0.dist-info/RECORD
