Metadata-Version: 2.1
Name: papermerge-restapi-client
Version: 1.0.0
Summary: Papermerge REST API
Home-page: 
Author: OpenAPI Generator community
Author-email: team@openapitools.org
Keywords: OpenAPI,OpenAPI-Generator,Papermerge REST API
Requires-Python: >=3.7
Requires-Dist: urllib3 (>=1.15)
Requires-Dist: certifi
Requires-Dist: python-dateutil
Requires-Dist: frozendict (>=2.0.3)
Requires-Dist: typing-extensions
